LICENSE
MANIFEST.in
README.md
dnsimple-dyndns
setup.py
dnsimple_dyndns/__init__.py
dnsimple_dyndns/dnsimple.py
dnsimple_dyndns/external_ip.py
dnsimple_dyndns.egg-info/PKG-INFO
dnsimple_dyndns.egg-info/SOURCES.txt
dnsimple_dyndns.egg-info/dependency_links.txt
dnsimple_dyndns.egg-info/entry_points.txt
dnsimple_dyndns.egg-info/requires.txt
dnsimple_dyndns.egg-info/top_level.txt