Metadata-Version: 1.1
Name: dnsimple-dyndns
Version: 0.1
Summary: Dynamic DNS implementation, that relies on DNSimple.com.
Home-page: https://github.com/rafaelmartins/dnsimple-dyndns
Author: Rafael Goncalves Martins
Author-email: rafael@rafaelmartins.eng.br
License: BSD
Platform: UNKNOWN
Classifier: Development Status :: 3 - Alpha
Classifier: Environment :: Console
Classifier: License :: OSI Approved :: BSD License
Classifier: Operating System :: OS Independent
Classifier: Programming Language :: Python :: 2.7
